[{
  "id": 1,
  "name": "Gerrilee Dowber",
  "sex": "Female",
  "shelterId": 1
}, {
  "id": 2,
  "name": "Friedrich McIlhatton",
  "sex": "Male",
  "shelterId": 2
}, {
  "id": 3,
  "name": "Carmelina Cuvley",
  "sex": "Female",
  "shelterId": 1
}, {
  "id": 4,
  "name": "Tanya Bapty",
  "sex": "Female",
  "shelterId": 2
}, {
  "id": 5,
  "name": "Blanch Osman",
  "sex": "Female",
  "shelterId": 2
}, {
  "id": 6,
  "name": "Alyss Iannazzi",
  "sex": "Female",
  "shelterId": 2
}, {
  "id": 7,
  "name": "Danika Iveson",
  "sex": "Female",
  "shelterId": 2
}, {
  "id": 8,
  "name": "Joel Pilipyak",
  "sex": "Male",
  "shelterId": 2
}, {
  "id": 9,
  "name": "Ephraim McVeigh",
  "sex": "Male",
  "shelterId": 2
}, {
  "id": 10,
  "name": "Hinze Shimwell",
  "sex": "Male",
  "shelterId": 2
}, {
  "id": 11,
  "name": "Veriee Pere",
  "sex": "Female",
  "shelterId": 2
}, {
  "id": 12,
  "name": "Germana Snaith",
  "sex": "Female",
  "shelterId": 1
}, {
  "id": 13,
  "name": "Rochelle Tampen",
  "sex": "Female",
  "shelterId": 1
}, {
  "id": 14,
  "name": "Elfreda Mantle",
  "sex": "Female",
  "shelterId": 1
}, {
  "id": 15,
  "name": "Sarita Fincke",
  "sex": "Female",
  "shelterId": 2
}, {
  "id": 16,
  "name": "Van Sesser",
  "sex": "Male",
  "shelterId": 2
}, {
  "id": 17,
  "name": "Nestor Burnsell",
  "sex": "Male",
  "shelterId": 2
}, {
  "id": 18,
  "name": "Gwenore Normanton",
  "sex": "Female",
  "shelterId": 1
}, {
  "id": 19,
  "name": "Grange Filyakov",
  "sex": "Male",
  "shelterId": 2
}, {
  "id": 20,
  "name": "Stephana Lorrimer",
  "sex": "Female",
  "shelterId": 2
}, {
  "id": 21,
  "name": "Pammie Treker",
  "sex": "Female",
  "shelterId": 2
}, {
  "id": 22,
  "name": "Deane Watterson",
  "sex": "Male",
  "shelterId": 2
}, {
  "id": 23,
  "name": "Xylina Ault",
  "sex": "Female",
  "shelterId": 2
}, {
  "id": 24,
  "name": "Katalin Littlecote",
  "sex": "Female",
  "shelterId": 1
}, {
  "id": 25,
  "name": "Temple Ballinger",
  "sex": "Male",
  "shelterId": 2
}, {
  "id": 26,
  "name": "Paten Accum",
  "sex": "Male",
  "shelterId": 2
}, {
  "id": 27,
  "name": "Pauly O'Luney",
  "sex": "Female",
  "shelterId": 2
}, {
  "id": 28,
  "name": "Foss Farmloe",
  "sex": "Male",
  "shelterId": 2
}, {
  "id": 29,
  "name": "Yevette McAnellye",
  "sex": "Female",
  "shelterId": 1
}, {
  "id": 30,
  "name": "Gena Trow",
  "sex": "Female",
  "shelterId": 2
}]
